colabvenv/__init__.py
colabvenv/colabvenv.py
colabvenv-0.1.dist-info/LICENSE
colabvenv-0.1.dist-info/METADATA
colabvenv-0.1.dist-info/WHEEL
colabvenv-0.1.dist-info/top_level.txt
colabvenv-0.1.dist-info/RECORD
