Metadata-Version: 2.1
Name: colabvenv
Version: 0.1
Summary: A package that creates python 3.8 virtual environments on Google  Colab and Jupyter Notebooks in Linux OS or WSL Systems.
Home-page: https://github.com/athasdelis/colabvenv
Author: Athanasios Delis, Stylianos Kandylakis
Author-email: athanasiosdelis@gmail.com, stelkcand@gmail.com
Classifier: Programming Language :: Python :: 3.8
Classifier: License :: OSI Approved :: MIT License
Classifier: Operating System :: POSIX
Classifier: Operating System :: Microsoft :: Windows :: Windows 10
Classifier: Operating System :: Microsoft :: Windows :: Windows 11
Classifier: Intended Audience :: Developers
Classifier: Intended Audience :: Science/Research
Requires-Python: >=3.6
License-File: LICENSE
